gameServerBackend/__init__.py
gameServerBackend/gameServer.py
gameServerBackend/requestProcessor/__init__.py
gameServerBackend/requestProcessor/dataTypes.py
gameServerBackend/requestProcessor/errors.py
gameServerBackend/requestProcessor/game.py
gameServerBackend/requestProcessor/interactions.py
gameServerBackend/requestProcessor/requestProcess.py
gameServerBackend/server/__init__.py
gameServerBackend/server/factoryAndProtocol.py
gameServerBackend/server/server.py
gameServerBackend/server/tokenStorage.py
game_server_backend/__init__.py
game_server_backend/gameServer.py
game_server_backend/requestProcessor/__init__.py
game_server_backend/requestProcessor/dataTypes.py
game_server_backend/requestProcessor/errors.py
game_server_backend/requestProcessor/game.py
game_server_backend/requestProcessor/interactions.py
game_server_backend/requestProcessor/requestProcess.py
game_server_backend/server/__init__.py
game_server_backend/server/factoryAndProtocol.py
game_server_backend/server/server.py
game_server_backend/server/tokenStorage.py
gameServerBackend-0.0.4.dist-info/LICENSE
gameServerBackend-0.0.4.dist-info/METADATA
gameServerBackend-0.0.4.dist-info/WHEEL
gameServerBackend-0.0.4.dist-info/top_level.txt
gameServerBackend-0.0.4.dist-info/RECORD
