Metadata-Version: 2.1
Name: gameServerBackend
Version: 0.0.4
Summary: A framework that interfaces games with websockets
Home-page: https://github.com/hydrogen602/gameServerBackend
Author: hydrogen602
Author-email: hydrogen31415@gmail.com
License: UNKNOWN
Platform: UNKNOWN
Classifier: Programming Language :: Python :: 3
Classifier: License :: OSI Approved :: GNU General Public License v3 (GPLv3)
Classifier: Operating System :: OS Independent
Classifier: Framework :: Twisted
Requires-Python: >=3.7
